Metadata-Version: 1.1
Name: kb-transaction
Version: 0.0.3.1
Summary: Crawling KB bank transaction with IE Selenium
Home-page: https://github.com/beomi/kb-transaction
Author: Junbum Lee
Author-email: jun@beomi.net
License: MIT
Download-URL: https://github.com/beomi/kb_transaction/archive/0.0.3.1.tar.gz
Platform: UNKNOWN
